iterfiles/__init__.py
iterfiles/_iterfiles.py
iterfiles-0.1.0.dist-info/LICENSE
iterfiles-0.1.0.dist-info/METADATA
iterfiles-0.1.0.dist-info/WHEEL
iterfiles-0.1.0.dist-info/top_level.txt
iterfiles-0.1.0.dist-info/zip-safe
iterfiles-0.1.0.dist-info/RECORD
