Metadata-Version: 2.1
Name: iterfiles
Version: 0.1.0
Summary: Find and process files in a Pythonic way, without boilerplate code.
Home-page: https://github.com/alexanderlukanin13/iterfiles
Author: Alexander Lukanin
Author-email: alexander.lukanin.13@gmail.com
License: MIT license
Keywords: file,pattern,directory,tree,traverse,find,convert
Platform: UNKNOWN
Classifier: Development Status :: 2 - Pre-Alpha
Classifier: License :: OSI Approved :: MIT License
Classifier: Programming Language :: Python :: 3
Classifier: Programming Language :: Python :: 3.6
Classifier: Programming Language :: Python :: 3.7
Classifier: Programming Language :: Python :: 3.8
Classifier: Programming Language :: Python :: 3.9
Requires-Python: >=3.6
